{
  "coda_doc_id": "J4v88b4mmW",
  "coda_table_id": "grid-jGQkuHb9Y9",
  "coda_table_name": "Shine Topics",
  "row_count": 10,
  "rows": [
    {
      "Contained Topics": "guapacha 2"
    },
    {
      "Contained Topics": "guapacha 1"
    },
    {
      "Contained Topics": "rush"
    },
    {
      "Contained Topics": "body"
    },
    {
      "Contained Topics": "arm"
    },
    {
      "Contained Topics": "groove"
    },
    {
      "Contained Topics": "flare"
    },
    {
      "Contained Topics": "twist"
    },
    {
      "Contained Topics": "insert"
    },
    {
      "Contained Topics": "basic"
    }
  ]
}